dagster_polytomic/__init__.py
dagster_polytomic/component.py
dagster_polytomic/objects.py
dagster_polytomic/py.typed
dagster_polytomic/translation.py
dagster_polytomic/version.py
dagster_polytomic/workspace.py
dagster_polytomic-0.28.13.dist-info/licenses/LICENSE
dagster_polytomic-0.28.13.dist-info/METADATA
dagster_polytomic-0.28.13.dist-info/WHEEL
dagster_polytomic-0.28.13.dist-info/top_level.txt
dagster_polytomic-0.28.13.dist-info/RECORD
