Metadata-Version: 2.4
Name: dagster_polytomic
Version: 0.28.13
Summary: Package for integrating Polytomic with Dagster.
Home-page: https://github.com/dagster-io/dagster/tree/master/python_modules/libraries/dagster-polytomic
Author: Dagster Labs
Author-email: hello@dagsterlabs.com
License: Apache-2.0
Classifier: Programming Language :: Python :: 3.10
Classifier: Programming Language :: Python :: 3.11
Classifier: Programming Language :: Python :: 3.12
Classifier: Programming Language :: Python :: 3.13
Classifier: Programming Language :: Python :: 3.14
Classifier: License :: OSI Approved :: Apache Software License
Classifier: Operating System :: OS Independent
Requires-Python: >=3.10,<3.15
License-File: LICENSE
Requires-Dist: dagster==1.12.13
Requires-Dist: polytomic>=1.11.3
Dynamic: author
Dynamic: author-email
Dynamic: classifier
Dynamic: home-page
Dynamic: license
Dynamic: license-file
Dynamic: requires-dist
Dynamic: requires-python
Dynamic: summary
